ir_kit-1.0.1rc0.dist-info/DESCRIPTION.rst
ir_kit-1.0.1rc0.dist-info/METADATA
ir_kit-1.0.1rc0.dist-info/RECORD
ir_kit-1.0.1rc0.dist-info/WHEEL
ir_kit-1.0.1rc0.dist-info/entry_points.txt
ir_kit-1.0.1rc0.dist-info/metadata.json
ir_kit-1.0.1rc0.dist-info/top_level.txt
irkit/__init__.py
irkit/plot/__init__.py
irkit/plot/trecplot.py
irkit/query/__init__.py
irkit/query/elasticsearch.py
irkit/trec/__init__.py
irkit/trec/qrels.py
irkit/trec/results.py
irkit/trec/run.py
