Metadata-Version: 2.0
Name: ir-kit
Version: 1.0.1rc0
Summary: Utilities for information retrieval in python
Home-page: https://github.com/hscells/ir-kit
Author: Harry Scells
Author-email: harryscells@gmail.com
License: MIT
Keywords: information retrieval ir
Platform: UNKNOWN
Classifier: Development Status :: 4 - Beta
Classifier: Intended Audience :: Developers
Classifier: Topic :: Software Development
Classifier: License :: OSI Approved :: MIT License
Classifier: Programming Language :: Python :: 3.3
Classifier: Programming Language :: Python :: 3.4
Classifier: Programming Language :: Python :: 3.5
Classifier: Programming Language :: Python :: 3.6
Requires-Dist: matplotlib
Requires-Dist: numpy
